pyrehau_neasmart/__init__.py
pyrehau_neasmart/const.py
pyrehau_neasmart/device.py
pyrehau_neasmart/exceptions.py
pyrehau_neasmart/heatarea.py
pyrehau_neasmart/iodevice.py
pyrehau_neasmart/utils.py
pyrehau_neasmart-0.0.8.dist-info/licenses/LICENSE
pyrehau_neasmart-0.0.8.dist-info/METADATA
pyrehau_neasmart-0.0.8.dist-info/WHEEL
pyrehau_neasmart-0.0.8.dist-info/top_level.txt
pyrehau_neasmart-0.0.8.dist-info/RECORD
