Metadata-Version: 2.4
Name: pyrehau_neasmart
Version: 0.0.8
Summary: A python package to interact with Rehaut Nea Smart interface
Home-page: https://github.com/Jeoffreybauvin/pyrehau_neasmart
Author: Jeoffrey BAUVIN
Author-email: jeoffrey.bauvin@gmail.com
Classifier: Programming Language :: Python :: 3
Classifier: License :: OSI Approved :: MIT License
Classifier: Operating System :: OS Independent
Requires-Python: >=3.6
License-File: LICENSE
Requires-Dist: requests
Dynamic: author
Dynamic: author-email
Dynamic: classifier
Dynamic: description
Dynamic: description-content-type
Dynamic: home-page
Dynamic: license-file
Dynamic: requires-dist
Dynamic: requires-python
Dynamic: summary
